setup.py
salar/__init__.py
salar/apidoc.py
salar/application.py
salar/cli.py
salar/run.py
salar/sample.py
salar/storage.py
salar/sugar.py
salar/webapi.py
salar.egg-info/PKG-INFO
salar.egg-info/SOURCES.txt
salar.egg-info/dependency_links.txt
salar.egg-info/entry_points.txt
salar.egg-info/top_level.txt
salar/plugin/__init__.py
salar/plugin/sqlmodel.py
test/test_sugar.py