Metadata-Version: 1.0
Name: salar
Version: 0.0.3
Summary: Web framework and Tookit for generating command line interfaces
Home-page: https://github.com/qorzj/salar
Author: qorzj
Author-email: inull@qq.com
License: MIT
Keywords: salar web cli
Platform: any
